[
  {
    "filename": "audio_tradeoff_page1.png",
    "url": "/api/images/2601.22143/audio_tradeoff_page1.png",
    "source": "arxiv"
  },
  {
    "filename": "comp_duration_v4_page1.png",
    "url": "/api/images/2601.22143/comp_duration_v4_page1.png",
    "source": "arxiv"
  },
  {
    "filename": "comp_event2_v2_licensed_page1.png",
    "url": "/api/images/2601.22143/comp_event2_v2_licensed_page1.png",
    "source": "arxiv"
  },
  {
    "filename": "comp_event_v3_page1.png",
    "url": "/api/images/2601.22143/comp_event_v3_page1.png",
    "source": "arxiv"
  },
  {
    "filename": "comp_generalization_v4_licensed_page1.png",
    "url": "/api/images/2601.22143/comp_generalization_v4_licensed_page1.png",
    "source": "arxiv"
  },
  {
    "filename": "comp_quality_v4_licensed_page1.png",
    "url": "/api/images/2601.22143/comp_quality_v4_licensed_page1.png",
    "source": "arxiv"
  },
  {
    "filename": "dataset_v6_page1.png",
    "url": "/api/images/2601.22143/dataset_v6_page1.png",
    "source": "arxiv"
  },
  {
    "filename": "lip_augmentation_v1_page1.png",
    "url": "/api/images/2601.22143/lip_augmentation_v1_page1.png",
    "source": "arxiv"
  },
  {
    "filename": "model_train_v4_page1.png",
    "url": "/api/images/2601.22143/model_train_v4_page1.png",
    "source": "arxiv"
  },
  {
    "filename": "supp_latent_mask_v2_page1.png",
    "url": "/api/images/2601.22143/supp_latent_mask_v2_page1.png",
    "source": "arxiv"
  },
  {
    "filename": "teaser_v6_page1.png",
    "url": "/api/images/2601.22143/teaser_v6_page1.png",
    "source": "arxiv"
  },
  {
    "filename": "user_study_v3_page1.png",
    "url": "/api/images/2601.22143/user_study_v3_page1.png",
    "source": "arxiv"
  }
]